CHANGES.txt
LICENSE.txt
MANIFEST.in
README.rst
setup.py
MongoTest.egg-info/PKG-INFO
MongoTest.egg-info/SOURCES.txt
MongoTest.egg-info/dependency_links.txt
MongoTest.egg-info/requires.txt
MongoTest.egg-info/top_level.txt
mongo_test/__init__.py
mongo_test/fixtures.py
mongo_test/handlers.py
test/test_user.py