Metadata-Version: 1.0
Name: MongoTest
Version: 0.1.2
Summary: A Python library to ease testing applications that rely on
Home-page: https://github.com/idbentley/mongo_test
Author: idbentley
Author-email: ian.bentley@gmail.com
License: LICENSE.txt
Keywords: python MongoDB fixture test
Platform: UNKNOWN
